lb/nightly/db/__init__.py
lb/nightly/db/database.py
lb/nightly/db/utils.py
lb_nightly_db-0.2.0.dist-info/LICENSE
lb_nightly_db-0.2.0.dist-info/WHEEL
lb_nightly_db-0.2.0.dist-info/METADATA
lb_nightly_db-0.2.0.dist-info/RECORD
