Metadata-Version: 2.1
Name: lb-nightly-db
Version: 0.2.0
Summary: Database access layer for LHCb Nightly and Continuous Integration Build System
License: GPL-3.0-only
Author: Marco Clemencic
Author-email: marco.clemencic@cern.ch
Requires-Python: >=3.8,<4.0
Classifier: License :: OSI Approved :: GNU General Public License v3 (GPLv3)
Classifier: Programming Language :: Python :: 3
Classifier: Programming Language :: Python :: 3.8
Classifier: Programming Language :: Python :: 3.9
Classifier: Programming Language :: Python :: 3.10
Requires-Dist: cloudant (>=2.14.0,<3.0.0)
Requires-Dist: lb-nightly-configuration (>=0.3,<0.4)
